README.rst
_description.org
lh-agpl3-LICENSE.txt
pyproject.toml
setup.py
bin/bx-platformInfoManage.cs
bin/platformBasesUpdate.cs
bin/platformStub.cs
bisos/__init__.py
bisos.platform.egg-info/PKG-INFO
bisos.platform.egg-info/SOURCES.txt
bisos.platform.egg-info/dependency_links.txt
bisos.platform.egg-info/not-zip-safe
bisos.platform.egg-info/requires.txt
bisos.platform.egg-info/top_level.txt
bisos/platform/__init__.py
bisos/platform/bxPlatformConfig.py
bisos/platform/bxPlatformThis.py
bisos/platform/platformBases.py
bisos/platform/platformBases_csu.py
bisos/platform/platformBpo.py
bisos/platform-config/admin/sitePlatformManage.py
bisos/platform-config/pkgInfo/fp/anyName/_tree_
bisos/platform-config/pkgInfo/fp/anyName/value
bisos/platform-config/pkgInfo/fp/bisosGroupName/_tree_
bisos/platform-config/pkgInfo/fp/bisosGroupName/value
bisos/platform-config/pkgInfo/fp/bisosUserName/_tree_
bisos/platform-config/pkgInfo/fp/bisosUserName/value
bisos/platform-config/pkgInfo/fp/bystarGroupName/_tree_
bisos/platform-config/pkgInfo/fp/bystarGroupName/value
bisos/platform-config/pkgInfo/fp/bystarUserName/_tree_
bisos/platform-config/pkgInfo/fp/bystarUserName/value
bisos/platform-config/pkgInfo/fp/icmsPkgName/_tree_
bisos/platform-config/pkgInfo/fp/icmsPkgName/value
bisos/platform-config/pkgInfo/fp/platformControlBaseDir/_tree_
bisos/platform-config/pkgInfo/fp/platformControlBaseDir/value
bisos/platform-config/pkgInfo/fp/rootDir_bisos/_tree_
bisos/platform-config/pkgInfo/fp/rootDir_bisos/value
bisos/platform-config/pkgInfo/fp/rootDir_bxo/_tree_
bisos/platform-config/pkgInfo/fp/rootDir_bxo/value
bisos/platform-config/pkgInfo/fp/rootDir_deRun/_tree_
bisos/platform-config/pkgInfo/fp/rootDir_deRun/value
bisos/platform-config/pkgInfo/fp/rootDir_foreignBxo/_tree_
bisos/platform-config/pkgInfo/fp/rootDir_foreignBxo/value
bisos/platform-config/pkgInfo/fp/rootDir_provisioners/_tree_
bisos/platform-config/pkgInfo/fp/rootDir_provisioners/value